setup.py
django_quicktag.egg-info/PKG-INFO
django_quicktag.egg-info/SOURCES.txt
django_quicktag.egg-info/dependency_links.txt
django_quicktag.egg-info/top_level.txt
quicktag/__init__.py
quicktag/parser.py