Metadata-Version: 1.0
Name: django-quicktag
Version: 0.6
Summary: django-quicktag - Easily create templatetags that takes args and kwargs
Home-page: http://github.com/ricobl/django-quicktag/
Author: Enrico Batista da Luz
Author-email: rico.bl@gmail.com
License: UNKNOWN
Platform: UNKNOWN
